{
  "status": 200,
  "data": {
    "id": 3,
    "msg_target_id": 1,
    "manager_id": 1,
    "receiver_id": 2,
    "team_id": 1,
    "email_subject": "Picnic Saturday",
    "email_message": "{\"header\"=>\"Dragon Rage\", \"section1\"=>\"imagine you are writing an email. you are in front of the computer. you are operating the computer, clicking a mouse and typing on a keyboard, but the message will be sent to a human over the internet. so you are working before the computer, but with a human behind the computer.\", \"button\"=>\"Count me in!\"}",
    "template_id": 0,
    "sms_message": "Bring Drinks to the Picnic this Saturday",
    "message_params": {
      "public_token": "42c50c442ee3ca01378e",
      "receiver_sso_id": "55357499",
      "email_subject": "Picnic Saturday",
      "email_message": {
        "header": "Dragon Rage",
        "section1": "imagine you are writing an email. you are in front of the computer. you are operating the computer, clicking a mouse and typing on a keyboard, but the message will be sent to a human over the internet. so you are working before the computer, but with a human behind the computer.",
        "button": "Count me in!"
      },
      "template_id": "XXX-f986df533e514f978f4460bedca50db0",
      "sms_message": "Bring Drinks to the Picnic this Saturday"
    },
    "created_at": "2019-06-05T22:48:52.908Z",
    "updated_at": "2019-06-05T22:48:52.920Z"
  },
  "error": null
}